.gitignore
LICENSE
README.rst
setup.cfg
setup.py
.circleci/config.yml
girder_xtk_demo/__init__.py
girder_xtk_demo.egg-info/PKG-INFO
girder_xtk_demo.egg-info/SOURCES.txt
girder_xtk_demo.egg-info/dependency_links.txt
girder_xtk_demo.egg-info/entry_points.txt
girder_xtk_demo.egg-info/not-zip-safe
girder_xtk_demo.egg-info/requires.txt
girder_xtk_demo.egg-info/top_level.txt
girder_xtk_demo/web_client/XtkView.js
girder_xtk_demo/web_client/main.js
girder_xtk_demo/web_client/package.json
girder_xtk_demo/web_client/xtkItemView.styl
girder_xtk_demo/web_client/xtk_demo_viewer.pug