Metadata-Version: 2.1
Name: girder-xtk-demo
Version: 0.4.0
Summary: Demo plugin to show very basic integration of girder and XTK
Home-page: https://github.com/girder/girder_xtk_demo
Author: Kitware, Inc.
Author-email: kitware@kitware.com
License: Apache Software License 2.0
Keywords: girder-plugin,girder_xtk_demo
Platform: UNKNOWN
Classifier: Development Status :: 3 - Alpha
Classifier: License :: OSI Approved :: Apache Software License
Classifier: Natural Language :: English
Classifier: Programming Language :: Python :: 2
Classifier: Programming Language :: Python :: 2.7
Classifier: Programming Language :: Python :: 3
Classifier: Programming Language :: Python :: 3.5
Classifier: Programming Language :: Python :: 3.6
Classifier: Programming Language :: Python :: 3.7
